data/wordlist.txt
wordhash/__init__.py
wordhash/wordhash.py
wordhash/data/wordlist.txt
wordhash-0.1.1.dist-info/LICENSE.md
wordhash-0.1.1.dist-info/METADATA
wordhash-0.1.1.dist-info/WHEEL
wordhash-0.1.1.dist-info/entry_points.txt
wordhash-0.1.1.dist-info/top_level.txt
wordhash-0.1.1.dist-info/RECORD
