Metadata-Version: 2.1
Name: wordhash
Version: 0.1.1
Summary: Get a string of English words as a fingerprint of any input data
Author-email: Jesse Bulson-Lewis <j.bl@posteo.org>
License: LGPLv3
Project-URL: Homepage, https://github.com/jessebl/wordhash
Classifier: Programming Language :: Python :: 3
Classifier: License :: OSI Approved :: GNU Lesser General Public License v3 (LGPLv3)
Classifier: Operating System :: OS Independent
Requires-Python: >=3.6
License-File: LICENSE.md
Requires-Dist: bitstring
